DataBase.py
Model.py
ParaAnalyzer.py
__init__.py
PyraAnalyzer-1.0.2.dist-info/LICENSE
PyraAnalyzer-1.0.2.dist-info/METADATA
PyraAnalyzer-1.0.2.dist-info/WHEEL
PyraAnalyzer-1.0.2.dist-info/top_level.txt
PyraAnalyzer-1.0.2.dist-info/RECORD
